{
  "info": {
    "_postman_id": "ce14512d-8250-42e0-978b-15050905d9f0",
    "name": "In-Warranty collection Copy",
    "schema": "https://schema.getpostman.com/json/collection/v2.1.0/collection.json",
    "_exporter_id": "20378162",
    "_collection_link": "https://go.postman.co/collection/20378162-ce14512d-8250-42e0-978b-15050905d9f0?source=collection_link"
  },
  "item": [
    {
      "name": "loginAPI request",
      "event": [
        {
          "listen": "test",
          "script": {
            "exec": [
              "console.log(\"inside post request\")\r",
              "\r",
              "pm.test(\"verify if the status code is 200\",function (){\r",
              "\r",
              "pm.response.to.have.status(200)\r",
              "})\r",
              "\r",
              "pm.test(\"verify if the response time is less than 300ms\", function (){\r",
              "\r",
              "pm.expect(pm.response.responseTime).to.be.lessThan(300)\r",
              "})\r",
              "\r",
              "pm.test(\"verify if the response message is equal to success\", function (){\r",
              "pm.expect(pm.response.json().message).to.eql(\"Success\")\r",
              "})\r",
              "\r",
              "\r",
              "pm.test(\"verify the token is not null\", function (){\r",
              "    pm.expect(pm.response.json().data.token).to.not.eql(null)\r",
              "})\r",
              "\r",
              "\r",
              "const jsonSchema = {\r",
              "    \"type\": \"object\",\r",
              "  \"properties\": {\r",
              "    \"message\": {\r",
              "      \"type\": \"string\"\r",
              "    },\r",
              "    \"data\": {\r",
              "      \"type\": \"object\",\r",
              "      \"properties\": {\r",
              "        \"token\": {\r",
              "          \"type\": \"string\"\r",
              "        }\r",
              "      },\r",
              "      \"required\": [\r",
              "        \"token\"\r",
              "      ]\r",
              "    }\r",
              "  },\r",
              "  \"required\": [\r",
              "    \"message\",\r",
              "    \"data\"\r",
              "  ]\r",
              "}\r",
              "\r",
              "pm.test(\"Verify Json Schema\", function(){\r",
              "    pm.response.to.have.jsonSchema(jsonSchema)\r",
              "})\r",
              "\r",
              "console.log(pm.variables.get(\"username\"))\r",
              "var responseBody = pm.response.json();\r",
              "console.log(responseBody.data.token);\r",
              "pm.collectionVariables.set(\"fdtoken\",responseBody.data.token)\r",
              ""
            ],
            "type": "text/javascript",
            "packages": {},
            "requests": {}
          }
        },
        {
          "listen": "prerequest",
          "script": {
            "exec": [
              "console.log(\"inside pre request\")\r",
              "pm.variables.set(\"username\", \"sowmi\");"
            ],
            "type": "text/javascript",
            "packages": {},
            "requests": {}
          }
        }
      ],
      "request": {
        "method": "POST",
        "header": [],
        "body": {
          "mode": "raw",
          "raw": "{\r\n    \"username\": \"iamfd\",\r\n    \"password\": \"password\"\r\n}",
          "options": {
            "raw": {
              "language": "json"
            }
          }
        },
        "url": {
          "raw": "{{BASE_URL}}/login",
          "host": [
            "{{BASE_URL}}"
          ],
          "path": [
            "login"
          ]
        }
      },
      "response": []
    },
    {
      "name": "loginAPI request - Practice Negative scenario",
      "event": [
        {
          "listen": "test",
          "script": {
            "exec": [
              "console.log(\"Running Negative test\")\r",
              "pm.test(\"Status code is 401\", function (){\r",
              "pm.expect(pm.response.code).to.eql(401)\r",
              "})\r",
              "pm.test(\"Verify the error message\", function (){\r",
              "    pm.expect(pm.response.json().message).to.eql(\"Invalid username or password\")\r",
              "})"
            ],
            "type": "text/javascript",
            "packages": {},
            "requests": {}
          }
        },
        {
          "listen": "prerequest",
          "script": {
            "exec": [
              "console.log(\"inside pre request\")\r",
              "pm.variables.set(\"username\", \"sowmi\");\r",
              "var invalidUsername = \"iamfd123\"\r",
              "var invalidPassword = \"pass123\"\r",
              "pm.variables.set(\"invalidUsername\",invalidUsername)\r",
              "pm.variables.set(\"invalidPassword\",invalidPassword)"
            ],
            "type": "text/javascript",
            "packages": {},
            "requests": {}
          }
        }
      ],
      "request": {
        "method": "POST",
        "header": [],
        "body": {
          "mode": "raw",
          "raw": "{\r\n    \"username\": \"{{invalidUsername}}\",\r\n    \"password\": \"{{invalidPassword}}\"\r\n}",
          "options": {
            "raw": {
              "language": "json"
            }
          }
        },
        "url": {
          "raw": "{{BASE_URL}}/login",
          "host": [
            "{{BASE_URL}}"
          ],
          "path": [
            "login"
          ]
        }
      },
      "response": []
    },
    {
      "name": "loginAPI request-Practice",
      "event": [
        {
          "listen": "test",
          "script": {
            "exec": [
              "pm.test(\"Status code is 200\", function () {\r",
              "    pm.response.to.have.status(200);\r",
              "})\r",
              "pm.test(\"Response message is success\", function (){\r",
              "    pm.expect(pm.response.json().message).to.eql(\"Success\")\r",
              "})\r",
              "\r",
              "pm.test(\"Token is valid \", function (){\r",
              "    var token = pm.response.json().data.token\r",
              "    pm.expect(token.split(\".\").length).to.eql(3)\r",
              "    pm.collectionVariables.set(\"fdtoken\", token)\r",
              "})\r",
              "const schema = {\r",
              "    \"type\": \"object\",\r",
              "  \"properties\": {\r",
              "    \"message\": {\r",
              "      \"type\": \"string\"\r",
              "    },\r",
              "    \"data\": {\r",
              "      \"type\": \"object\",\r",
              "      \"properties\": {\r",
              "        \"token\": {\r",
              "          \"type\": \"string\"\r",
              "        }\r",
              "      },\r",
              "      \"required\": [\r",
              "        \"token\"\r",
              "      ]\r",
              "    }\r",
              "  },\r",
              "  \"required\": [\r",
              "    \"message\",\r",
              "    \"data\"\r",
              "  ]\r",
              "}\r",
              "pm.test(\"Validate the JSON Schema\", function () {\r",
              "    var jsonData = pm.response.json();\r",
              "    pm.expect(jsonData).to.have.jsonSchema(schema);\r",
              "})\r",
              "\r",
              "pm.test(\"Validate response time is less than 300\", function (){\r",
              "    pm.expect(pm.response.responseTime).to.be.below(300);\r",
              "})\r",
              "\r",
              ""
            ],
            "type": "text/javascript",
            "packages": {},
            "requests": {}
          }
        },
        {
          "listen": "prerequest",
          "script": {
            "exec": [
              "console.log(\"inside pre request\")\r",
              "pm.variables.set(\"username\", \"sowmi\");"
            ],
            "type": "text/javascript",
            "packages": {},
            "requests": {}
          }
        }
      ],
      "request": {
        "method": "POST",
        "header": [],
        "body": {
          "mode": "raw",
          "raw": "{\r\n    \"username\": \"iamfd\",\r\n    \"password\": \"password\"\r\n}",
          "options": {
            "raw": {
              "language": "json"
            }
          }
        },
        "url": {
          "raw": "{{BASE_URL}}/login",
          "host": [
            "{{BASE_URL}}"
          ],
          "path": [
            "login"
          ]
        }
      },
      "response": []
    },
    {
      "name": "userdetails",
      "event": [
        {
          "listen": "test",
          "script": {
            "exec": [
              "pm.test(\"Status code is 200\", function () {\r",
              "    pm.response.to.have.status(200);\r",
              "})\r",
              "\r",
              "pm.test(\"Response time is less than 200ms\", function () {\r",
              "    pm.expect(pm.response.responseTime).to.be.below(200);\r",
              "})\r",
              "\r",
              "pm.test(\"Response body contains user details\", function () {\r",
              "    pm.expect(pm.response.json().message).to.eql(\"Success\");\r",
              "    pm.expect(pm.response.json().data).to.have.property(\"id\");\r",
              "    pm.expect(pm.response.json().data).to.have.property(\"first_name\");\r",
              "    pm.expect(pm.response.json().data).to.have.property(\"last_name\");\r",
              "    pm.expect(pm.response.json().data).to.have.property(\"login_id\");\r",
              "    pm.expect(pm.response.json().data).to.have.property(\"mobile_number\");\r",
              "    pm.expect(pm.response.json().data).to.have.property(\"email_id\");\r",
              "    pm.expect(pm.response.json().data).to.have.property(\"reset_password_date\");\r",
              "    pm.expect(pm.response.json().data).to.have.property(\"lock_status\");\r",
              "    pm.expect(pm.response.json().data).to.have.property(\"is_active\");\r",
              "    pm.expect(pm.response.json().data).to.have.property(\"mst_role_id\");\r",
              "    pm.expect(pm.response.json().data).to.have.property(\"mst_service_location_id\");\r",
              "    pm.expect(pm.response.json().data).to.have.property(\"created_at\");\r",
              "    pm.expect(pm.response.json().data).to.have.property(\"modified_at\");\r",
              "    pm.expect(pm.response.json().data).to.have.property(\"role_name\");\r",
              "    pm.expect(pm.response.json().data).to.have.property(\"service_location\");\r",
              "    pm.expect(pm.response.json().data.role_name).to.eql(\"FrontDesk\");\r",
              "    pm.expect(pm.response.json().data.service_location).to.eql(\"Service Center A\");\r",
              "    pm.expect(pm.response.json().data.mobile_number).to.eql(\"8899776655\");\r",
              "    pm.expect(pm.response.json().data.email_id).to.eql(\"mark@gmail.com\");\r",
              "})\r",
              "const schema = {\r",
              "\r",
              "  \"type\": \"object\",\r",
              "  \"properties\": {\r",
              "    \"message\": {\r",
              "      \"type\": \"string\"\r",
              "    },\r",
              "    \"data\": {\r",
              "      \"type\": \"object\",\r",
              "      \"properties\": {\r",
              "        \"id\": {\r",
              "          \"type\": \"integer\"\r",
              "        },\r",
              "        \"first_name\": {\r",
              "          \"type\": \"string\"\r",
              "        },\r",
              "        \"last_name\": {\r",
              "          \"type\": \"string\"\r",
              "        },\r",
              "        \"login_id\": {\r",
              "          \"type\": \"string\"\r",
              "        },\r",
              "        \"mobile_number\": {\r",
              "          \"type\": \"string\"\r",
              "        },\r",
              "        \"email_id\": {\r",
              "          \"type\": \"string\"\r",
              "        },\r",
              "        \"password\": {\r",
              "          \"type\": \"string\"\r",
              "        },\r",
              "        \"reset_password_date\": {\r",
              "          \"type\": \"null\"\r",
              "        },\r",
              "        \"lock_status\": {\r",
              "          \"type\": \"integer\"\r",
              "        },\r",
              "        \"is_active\": {\r",
              "          \"type\": \"integer\"\r",
              "        },\r",
              "        \"mst_role_id\": {\r",
              "          \"type\": \"integer\"\r",
              "        },\r",
              "        \"mst_service_location_id\": {\r",
              "          \"type\": \"integer\"\r",
              "        },\r",
              "        \"created_at\": {\r",
              "          \"type\": \"string\"\r",
              "        },\r",
              "        \"modified_at\": {\r",
              "          \"type\": \"string\"\r",
              "        },\r",
              "        \"role_name\": {\r",
              "          \"type\": \"string\"\r",
              "        },\r",
              "        \"service_location\": {\r",
              "          \"type\": \"string\"\r",
              "        }\r",
              "      },\r",
              "      \"required\": [\r",
              "        \"id\",\r",
              "        \"first_name\",\r",
              "        \"last_name\",\r",
              "        \"login_id\",\r",
              "        \"mobile_number\",\r",
              "        \"email_id\",\r",
              "        \"password\",\r",
              "        \"reset_password_date\",\r",
              "        \"lock_status\",\r",
              "        \"is_active\",\r",
              "        \"mst_role_id\",\r",
              "        \"mst_service_location_id\",\r",
              "        \"created_at\",\r",
              "        \"modified_at\",\r",
              "        \"role_name\",\r",
              "        \"service_location\"\r",
              "      ]\r",
              "    }\r",
              "  },\r",
              "  \"required\": [\r",
              "    \"message\",\r",
              "    \"data\"\r",
              "  ]\r",
              "}\r",
              "pm.test(\"validate JSON schema\", function () {\r",
              "var Jsonschema = pm.response.json();\r",
              "pm.expect(Jsonschema).to.have.jsonSchema(schema);\r",
              "})"
            ],
            "type": "text/javascript",
            "packages": {},
            "requests": {}
          }
        }
      ],
      "request": {
        "auth": {
          "type": "noauth"
        },
        "method": "GET",
        "header": [
          {
            "key": "Authorization",
            "value": "{{fdtoken}}"
          }
        ],
        "url": {
          "raw": "{{BASE_URL}}/userdetails",
          "host": [
            "{{BASE_URL}}"
          ],
          "path": [
            "userdetails"
          ]
        },
        "description": "Generated from cURL: curl 'http://64.227.160.186:9000/v1/userdetails' \\\r\n  -H 'Accept: application/json, text/plain, */*' \\\r\n  -H 'Accept-Language: en-US,en;q=0.9' \\\r\n  -H 'Authorization: eyJhbGciOiJIUzI1NiIsInR5cCI6IkpXVCJ9.eyJpZCI6NCwiZmlyc3RfbmFtZSI6ImZkIiwibGFzdF9uYW1lIjoiZmQiLCJsb2dpbl9pZCI6ImlhbWZkIiwibW9iaWxlX251bWJlciI6Ijg4OTk3NzY2NTUiLCJlbWFpbF9pZCI6Im1hcmtAZ21haWwuY29tIiwicGFzc3dvcmQiOiI1ZjRkY2MzYjVhYTc2NWQ2MWQ4MzI3ZGViODgyY2Y5OSIsInJlc2V0X3Bhc3N3b3JkX2RhdGUiOm51bGwsImxvY2tfc3RhdHVzIjowLCJpc19hY3RpdmUiOjEsIm1zdF9yb2xlX2lkIjo1LCJtc3Rfc2VydmljZV9sb2NhdGlvbl9pZCI6MSwiY3JlYXRlZF9hdCI6IjIwMjEtMTEtMDNUMDg6MDY6MjMuMDAwWiIsIm1vZGlmaWVkX2F0IjoiMjAyMS0xMS0wM1QwODowNjoyMy4wMDBaIiwicm9sZV9uYW1lIjoiRnJvbnREZXNrIiwic2VydmljZV9sb2NhdGlvbiI6IlNlcnZpY2UgQ2VudGVyIEEiLCJpYXQiOjE3ODA1NzE0NzN9.yS1xSq3RZ2RMtino6uciMYr4UWgWEudsULMj7gZZNnY' \\\r\n  -H 'Connection: keep-alive' \\\r\n  -H 'If-None-Match: W/\"1b6-cR2dclq1S8zJDBAsHCDA10lTBi4\"' \\\r\n  -H 'Origin: http://phoenix.techwithjatin.com' \\\r\n  -H 'Referer: http://phoenix.techwithjatin.com/' \\\r\n  -H 'User-Agent: Mozilla/5.0 (Windows NT 10.0; Win64; x64) AppleWebKit/537.36 (KHTML, like Gecko) Chrome/148.0.0.0 Safari/537.36 Edg/148.0.0.0' \\\r\n  --insecure"
      },
      "response": []
    },
    {
      "name": "userdetails _negative scenarios",
      "event": [
        {
          "listen": "test",
          "script": {
            "exec": [
              "pm.test(\"Status code is 401\", function () {\r",
              "    pm.response.to.have.status(401);\r",
              "})"
            ],
            "type": "text/javascript",
            "packages": {},
            "requests": {}
          }
        }
      ],
      "request": {
        "auth": {
          "type": "noauth"
        },
        "method": "GET",
        "header": [
          {
            "key": "Authorization",
            "value": ""
          }
        ],
        "url": {
          "raw": "{{BASE_URL}}/userdetails",
          "host": [
            "{{BASE_URL}}"
          ],
          "path": [
            "userdetails"
          ]
        },
        "description": "Generated from cURL: curl 'http://64.227.160.186:9000/v1/userdetails' \\\r\n  -H 'Accept: application/json, text/plain, */*' \\\r\n  -H 'Accept-Language: en-US,en;q=0.9' \\\r\n  -H 'Authorization: eyJhbGciOiJIUzI1NiIsInR5cCI6IkpXVCJ9.eyJpZCI6NCwiZmlyc3RfbmFtZSI6ImZkIiwibGFzdF9uYW1lIjoiZmQiLCJsb2dpbl9pZCI6ImlhbWZkIiwibW9iaWxlX251bWJlciI6Ijg4OTk3NzY2NTUiLCJlbWFpbF9pZCI6Im1hcmtAZ21haWwuY29tIiwicGFzc3dvcmQiOiI1ZjRkY2MzYjVhYTc2NWQ2MWQ4MzI3ZGViODgyY2Y5OSIsInJlc2V0X3Bhc3N3b3JkX2RhdGUiOm51bGwsImxvY2tfc3RhdHVzIjowLCJpc19hY3RpdmUiOjEsIm1zdF9yb2xlX2lkIjo1LCJtc3Rfc2VydmljZV9sb2NhdGlvbl9pZCI6MSwiY3JlYXRlZF9hdCI6IjIwMjEtMTEtMDNUMDg6MDY6MjMuMDAwWiIsIm1vZGlmaWVkX2F0IjoiMjAyMS0xMS0wM1QwODowNjoyMy4wMDBaIiwicm9sZV9uYW1lIjoiRnJvbnREZXNrIiwic2VydmljZV9sb2NhdGlvbiI6IlNlcnZpY2UgQ2VudGVyIEEiLCJpYXQiOjE3ODA1NzE0NzN9.yS1xSq3RZ2RMtino6uciMYr4UWgWEudsULMj7gZZNnY' \\\r\n  -H 'Connection: keep-alive' \\\r\n  -H 'If-None-Match: W/\"1b6-cR2dclq1S8zJDBAsHCDA10lTBi4\"' \\\r\n  -H 'Origin: http://phoenix.techwithjatin.com' \\\r\n  -H 'Referer: http://phoenix.techwithjatin.com/' \\\r\n  -H 'User-Agent: Mozilla/5.0 (Windows NT 10.0; Win64; x64) AppleWebKit/537.36 (KHTML, like Gecko) Chrome/148.0.0.0 Safari/537.36 Edg/148.0.0.0' \\\r\n  --insecure"
      },
      "response": []
    },
    {
      "name": "userdetails security check",
      "event": [
        {
          "listen": "test",
          "script": {
            "exec": [
              "console.log(\"Security check\")\r",
              "pm.test(\"Check if password is not returned\", function () {\r",
              "pm.expect(pm.response.jason().data).to.not.have(\"password\")\r",
              "})"
            ],
            "type": "text/javascript",
            "packages": {},
            "requests": {}
          }
        }
      ],
      "request": {
        "auth": {
          "type": "noauth"
        },
        "method": "GET",
        "header": [
          {
            "key": "Authorization",
            "value": "{{fdtoken}}"
          }
        ],
        "url": {
          "raw": "{{BASE_URL}}/userdetails",
          "host": [
            "{{BASE_URL}}"
          ],
          "path": [
            "userdetails"
          ]
        },
        "description": "Generated from cURL: curl 'http://64.227.160.186:9000/v1/userdetails' \\\r\n  -H 'Accept: application/json, text/plain, */*' \\\r\n  -H 'Accept-Language: en-US,en;q=0.9' \\\r\n  -H 'Authorization: eyJhbGciOiJIUzI1NiIsInR5cCI6IkpXVCJ9.eyJpZCI6NCwiZmlyc3RfbmFtZSI6ImZkIiwibGFzdF9uYW1lIjoiZmQiLCJsb2dpbl9pZCI6ImlhbWZkIiwibW9iaWxlX251bWJlciI6Ijg4OTk3NzY2NTUiLCJlbWFpbF9pZCI6Im1hcmtAZ21haWwuY29tIiwicGFzc3dvcmQiOiI1ZjRkY2MzYjVhYTc2NWQ2MWQ4MzI3ZGViODgyY2Y5OSIsInJlc2V0X3Bhc3N3b3JkX2RhdGUiOm51bGwsImxvY2tfc3RhdHVzIjowLCJpc19hY3RpdmUiOjEsIm1zdF9yb2xlX2lkIjo1LCJtc3Rfc2VydmljZV9sb2NhdGlvbl9pZCI6MSwiY3JlYXRlZF9hdCI6IjIwMjEtMTEtMDNUMDg6MDY6MjMuMDAwWiIsIm1vZGlmaWVkX2F0IjoiMjAyMS0xMS0wM1QwODowNjoyMy4wMDBaIiwicm9sZV9uYW1lIjoiRnJvbnREZXNrIiwic2VydmljZV9sb2NhdGlvbiI6IlNlcnZpY2UgQ2VudGVyIEEiLCJpYXQiOjE3ODA1NzE0NzN9.yS1xSq3RZ2RMtino6uciMYr4UWgWEudsULMj7gZZNnY' \\\r\n  -H 'Connection: keep-alive' \\\r\n  -H 'If-None-Match: W/\"1b6-cR2dclq1S8zJDBAsHCDA10lTBi4\"' \\\r\n  -H 'Origin: http://phoenix.techwithjatin.com' \\\r\n  -H 'Referer: http://phoenix.techwithjatin.com/' \\\r\n  -H 'User-Agent: Mozilla/5.0 (Windows NT 10.0; Win64; x64) AppleWebKit/537.36 (KHTML, like Gecko) Chrome/148.0.0.0 Safari/537.36 Edg/148.0.0.0' \\\r\n  --insecure"
      },
      "response": []
    },
    {
      "name": "countapirequest",
      "event": [
        {
          "listen": "test",
          "script": {
            "exec": [
              "pm.test(\"Response status code is 200\", function (){\r",
              "    pm.response.to.have.status(200)\r",
              "})\r",
              "\r",
              "pm.test(\"Response time is less than 200ms\", function (){\r",
              "pm.expect(pm.response.responseTime).to.be.below(200)\r",
              "})\r",
              "\r",
              "const schema = {\r",
              "  \"type\": \"object\",\r",
              "  \"properties\": {\r",
              "    \"message\": {\r",
              "      \"type\": \"string\"\r",
              "    },\r",
              "    \"data\": {\r",
              "      \"type\": \"array\",\r",
              "      \"items\": [\r",
              "        {\r",
              "          \"type\": \"object\",\r",
              "          \"properties\": {\r",
              "            \"label\": {\r",
              "              \"type\": \"string\"\r",
              "            },\r",
              "            \"key\": {\r",
              "              \"type\": \"string\"\r",
              "            },\r",
              "            \"count\": {\r",
              "              \"type\": \"integer\"\r",
              "            }\r",
              "          },\r",
              "          \"required\": [\r",
              "            \"label\",\r",
              "            \"key\",\r",
              "            \"count\"\r",
              "          ]\r",
              "        },\r",
              "        {\r",
              "          \"type\": \"object\",\r",
              "          \"properties\": {\r",
              "            \"label\": {\r",
              "              \"type\": \"string\"\r",
              "            },\r",
              "            \"key\": {\r",
              "              \"type\": \"string\"\r",
              "            },\r",
              "            \"count\": {\r",
              "              \"type\": \"integer\"\r",
              "            }\r",
              "          },\r",
              "          \"required\": [\r",
              "            \"label\",\r",
              "            \"key\",\r",
              "            \"count\"\r",
              "          ]\r",
              "        },\r",
              "        {\r",
              "          \"type\": \"object\",\r",
              "          \"properties\": {\r",
              "            \"label\": {\r",
              "              \"type\": \"string\"\r",
              "            },\r",
              "            \"key\": {\r",
              "              \"type\": \"string\"\r",
              "            },\r",
              "            \"count\": {\r",
              "              \"type\": \"integer\"\r",
              "            }\r",
              "          },\r",
              "          \"required\": [\r",
              "            \"label\",\r",
              "            \"key\",\r",
              "            \"count\"\r",
              "          ]\r",
              "        }\r",
              "      ]\r",
              "    }\r",
              "  },\r",
              "  \"required\": [\r",
              "    \"message\",\r",
              "    \"data\"\r",
              "  ]\r",
              "}  \r",
              "pm.test(\"validate JSON Schema\",function(){\r",
              "    var jsonschema = pm.response.json();\r",
              "    pm.expect(jsonschema).to.be.jsonSchema(schema)\r",
              "})\r",
              "\r",
              "pm.test(\"verify the message is success\", function () {\r",
              "//pm.response.to.have.jsonBody('{\"message\": \"Success\"}')\r",
              "pm.expect(pm.response.json().message).to.eql(\"Success\")\r",
              "})\r",
              "\r",
              "pm.test(\"verify the length of array is 3\", function () {\r",
              "    pm.expect(pm.response.json().data.length).to.eql(3)\r",
              "})\r",
              "\r",
              "pm.test(\"verify if the key is pending for delivery\",function(){\r",
              "    pm.expect(pm.response.json().data[0].key).to.eql(\"pending_for_delivery\")\r",
              "})\r",
              "\r",
              "pm.test(\"verify if the key is created today\",function(){\r",
              "    pm.expect(pm.response.json().data[1].key).to.eql(\"created_today\")\r",
              "})\r",
              "pm.test(\"verify if the key is Pending for FST assignment\", function(){\r",
              "    pm.expect(pm.response.json().data[2].key).to.eql(\"pending_fst_assignment\")\r",
              "})\r",
              "\r",
              "var Expected_Key =[\"pending_for_delivery\",\"created_today\",\"pending_fst_assignment\"]\r",
              "\r",
              "var Actual_Key = pm.response.json().data.map(item => item.key) \r",
              "\r",
              "pm.test(\"validate if the keys are present in the response data array\", function(){\r",
              "    pm.expect(Actual_Key).to.include.members(Expected_Key)\r",
              "})\r",
              "\r",
              "//pm.test(\"verify if the count is Number type or not\", function(){\r",
              "  //  pm.expect(typeof(pm.response.json().data[0].count)).to.be.equal(\"number\")\r",
              "//}) data[0] is hardcoding which is not good practice \r",
              "\r",
              "var dataitem = pm.response.json().data\r",
              "\r",
              "for(var i=0;i<dataitem.length;i++){\r",
              "  pm.test(\"verify if the count is Number type or not\", function(){ \r",
              "   pm.expect(typeof(dataitem[i].count)).to.be.eql(\"number\")\r",
              "\r",
              "})\r",
              "}\r",
              "\r",
              "\r",
              ""
            ],
            "type": "text/javascript",
            "packages": {},
            "requests": {}
          }
        }
      ],
      "request": {
        "method": "GET",
        "header": [
          {
            "key": "Accept",
            "value": "application/json, text/plain, */*"
          },
          {
            "key": "Accept-Language",
            "value": "en-US,en;q=0.9"
          },
          {
            "key": "Authorization",
            "value": "{{fdtoken}}"
          },
          {
            "key": "Connection",
            "value": "keep-alive"
          },
          {
            "key": "Origin",
            "value": "http://phoenix.techwithjatin.com"
          },
          {
            "key": "Referer",
            "value": "http://phoenix.techwithjatin.com/"
          },
          {
            "key": "User-Agent",
            "value": "Mozilla/5.0 (Windows NT 10.0; Win64; x64) AppleWebKit/537.36 (KHTML, like Gecko) Chrome/148.0.0.0 Safari/537.36 Edg/148.0.0.0"
          }
        ],
        "url": {
          "raw": "{{BASE_URL}}/dashboard/count",
          "host": [
            "{{BASE_URL}}"
          ],
          "path": [
            "dashboard",
            "count"
          ]
        },
        "description": "Generated from cURL: curl 'http://64.227.160.186:9000/v1/dashboard/count' \\\r\n  -H 'Accept: application/json, text/plain, */*' \\\r\n  -H 'Accept-Language: en-US,en;q=0.9' \\\r\n  -H 'Authorization: eyJhbGciOiJIUzI1NiIsInR5cCI6IkpXVCJ9.eyJpZCI6NCwiZmlyc3RfbmFtZSI6ImZkIiwibGFzdF9uYW1lIjoiZmQiLCJsb2dpbl9pZCI6ImlhbWZkIiwibW9iaWxlX251bWJlciI6Ijg4OTk3NzY2NTUiLCJlbWFpbF9pZCI6Im1hcmtAZ21haWwuY29tIiwicGFzc3dvcmQiOiI1ZjRkY2MzYjVhYTc2NWQ2MWQ4MzI3ZGViODgyY2Y5OSIsInJlc2V0X3Bhc3N3b3JkX2RhdGUiOm51bGwsImxvY2tfc3RhdHVzIjowLCJpc19hY3RpdmUiOjEsIm1zdF9yb2xlX2lkIjo1LCJtc3Rfc2VydmljZV9sb2NhdGlvbl9pZCI6MSwiY3JlYXRlZF9hdCI6IjIwMjEtMTEtMDNUMDg6MDY6MjMuMDAwWiIsIm1vZGlmaWVkX2F0IjoiMjAyMS0xMS0wM1QwODowNjoyMy4wMDBaIiwicm9sZV9uYW1lIjoiRnJvbnREZXNrIiwic2VydmljZV9sb2NhdGlvbiI6IlNlcnZpY2UgQ2VudGVyIEEiLCJpYXQiOjE3ODA1NzE0NzN9.yS1xSq3RZ2RMtino6uciMYr4UWgWEudsULMj7gZZNnY' \\\r\n  -H 'Connection: keep-alive' \\\r\n  -H 'Origin: http://phoenix.techwithjatin.com' \\\r\n  -H 'Referer: http://phoenix.techwithjatin.com/' \\\r\n  -H 'User-Agent: Mozilla/5.0 (Windows NT 10.0; Win64; x64) AppleWebKit/537.36 (KHTML, like Gecko) Chrome/148.0.0.0 Safari/537.36 Edg/148.0.0.0' \\\r\n  --insecure"
      },
      "response": []
    },
    {
      "name": "masterapirequest",
      "event": [
        {
          "listen": "test",
          "script": {
            "exec": [
              "pm.test(\"verify the specified master keys are present or not\", function (){\r",
              "    pm.expect(pm.response.json().data).to.have.all.keys(\"mst_oem\", \"mst_model\",\"mst_product\",\"mst_problem\")\r",
              "    })\r",
              "\r",
              "    var Expected_Key = [\"mst_oem\", \"mst_model\",\"mst_product\",\"mst_problem\"]\r",
              "\r",
              "    Expected_Key.forEach(function(item){\r",
              "        pm.test(\"verify the response body contains the key \"+item, function(){\r",
              "            let jsonres = pm.response.json()\r",
              "            pm.expect(jsonres.data).to.have.property(item)\r",
              "\r",
              "    })\r",
              "    })\r",
              "\r",
              "    pm.test(\"verify if the key is storing a non empty array\", function (){\r",
              "            let jsondata = pm.response.json()\r",
              "            Expected_Key.forEach(function(item){\r",
              "                pm.expect(Array.isArray(jsondata.data[item])).to.be.true\r",
              "                pm.expect(jsondata.data[item].length).to.be.greaterThan(0)\r",
              "                \r",
              "            })\r",
              "    })"
            ],
            "type": "text/javascript",
            "packages": {},
            "requests": {}
          }
        }
      ],
      "request": {
        "method": "POST",
        "header": [
          {
            "key": "Accept",
            "value": "application/json, text/plain, */*"
          },
          {
            "key": "Accept-Language",
            "value": "en-US,en;q=0.9"
          },
          {
            "key": "Authorization",
            "value": "eyJhbGciOiJIUzI1NiIsInR5cCI6IkpXVCJ9.eyJpZCI6NCwiZmlyc3RfbmFtZSI6ImZkIiwibGFzdF9uYW1lIjoiZmQiLCJsb2dpbl9pZCI6ImlhbWZkIiwibW9iaWxlX251bWJlciI6Ijg4OTk3NzY2NTUiLCJlbWFpbF9pZCI6Im1hcmtAZ21haWwuY29tIiwicGFzc3dvcmQiOiI1ZjRkY2MzYjVhYTc2NWQ2MWQ4MzI3ZGViODgyY2Y5OSIsInJlc2V0X3Bhc3N3b3JkX2RhdGUiOm51bGwsImxvY2tfc3RhdHVzIjowLCJpc19hY3RpdmUiOjEsIm1zdF9yb2xlX2lkIjo1LCJtc3Rfc2VydmljZV9sb2NhdGlvbl9pZCI6MSwiY3JlYXRlZF9hdCI6IjIwMjEtMTEtMDNUMDg6MDY6MjMuMDAwWiIsIm1vZGlmaWVkX2F0IjoiMjAyMS0xMS0wM1QwODowNjoyMy4wMDBaIiwicm9sZV9uYW1lIjoiRnJvbnREZXNrIiwic2VydmljZV9sb2NhdGlvbiI6IlNlcnZpY2UgQ2VudGVyIEEiLCJpYXQiOjE3ODA1NzE0NzN9.yS1xSq3RZ2RMtino6uciMYr4UWgWEudsULMj7gZZNnY"
          },
          {
            "key": "Connection",
            "value": "keep-alive"
          },
          {
            "key": "Content-Length",
            "value": "0"
          },
          {
            "key": "Content-Type",
            "value": "text/plain"
          },
          {
            "key": "Origin",
            "value": "http://phoenix.techwithjatin.com"
          },
          {
            "key": "Referer",
            "value": "http://phoenix.techwithjatin.com/"
          },
          {
            "key": "User-Agent",
            "value": "Mozilla/5.0 (Windows NT 10.0; Win64; x64) AppleWebKit/537.36 (KHTML, like Gecko) Chrome/148.0.0.0 Safari/537.36 Edg/148.0.0.0"
          }
        ],
        "url": {
          "raw": "{{BASE_URL}}/master",
          "host": [
            "{{BASE_URL}}"
          ],
          "path": [
            "master"
          ]
        },
        "description": "Generated from cURL: curl 'http://64.227.160.186:9000/v1/master' \\\r\n  -X 'POST' \\\r\n  -H 'Accept: application/json, text/plain, */*' \\\r\n  -H 'Accept-Language: en-US,en;q=0.9' \\\r\n  -H 'Authorization: eyJhbGciOiJIUzI1NiIsInR5cCI6IkpXVCJ9.eyJpZCI6NCwiZmlyc3RfbmFtZSI6ImZkIiwibGFzdF9uYW1lIjoiZmQiLCJsb2dpbl9pZCI6ImlhbWZkIiwibW9iaWxlX251bWJlciI6Ijg4OTk3NzY2NTUiLCJlbWFpbF9pZCI6Im1hcmtAZ21haWwuY29tIiwicGFzc3dvcmQiOiI1ZjRkY2MzYjVhYTc2NWQ2MWQ4MzI3ZGViODgyY2Y5OSIsInJlc2V0X3Bhc3N3b3JkX2RhdGUiOm51bGwsImxvY2tfc3RhdHVzIjowLCJpc19hY3RpdmUiOjEsIm1zdF9yb2xlX2lkIjo1LCJtc3Rfc2VydmljZV9sb2NhdGlvbl9pZCI6MSwiY3JlYXRlZF9hdCI6IjIwMjEtMTEtMDNUMDg6MDY6MjMuMDAwWiIsIm1vZGlmaWVkX2F0IjoiMjAyMS0xMS0wM1QwODowNjoyMy4wMDBaIiwicm9sZV9uYW1lIjoiRnJvbnREZXNrIiwic2VydmljZV9sb2NhdGlvbiI6IlNlcnZpY2UgQ2VudGVyIEEiLCJpYXQiOjE3ODA1NzE0NzN9.yS1xSq3RZ2RMtino6uciMYr4UWgWEudsULMj7gZZNnY' \\\r\n  -H 'Connection: keep-alive' \\\r\n  -H 'Content-Length: 0' \\\r\n  -H 'Content-Type: text/plain' \\\r\n  -H 'Origin: http://phoenix.techwithjatin.com' \\\r\n  -H 'Referer: http://phoenix.techwithjatin.com/' \\\r\n  -H 'User-Agent: Mozilla/5.0 (Windows NT 10.0; Win64; x64) AppleWebKit/537.36 (KHTML, like Gecko) Chrome/148.0.0.0 Safari/537.36 Edg/148.0.0.0' \\\r\n  --insecure"
      },
      "response": []
    },
    {
      "name": "jobcreate",
      "request": {
        "method": "POST",
        "header": [
          {
            "key": "Accept",
            "value": "application/json, text/plain, */*"
          },
          {
            "key": "Accept-Language",
            "value": "en-US,en;q=0.9"
          },
          {
            "key": "Authorization",
            "value": "eyJhbGciOiJIUzI1NiIsInR5cCI6IkpXVCJ9.eyJpZCI6NCwiZmlyc3RfbmFtZSI6ImZkIiwibGFzdF9uYW1lIjoiZmQiLCJsb2dpbl9pZCI6ImlhbWZkIiwibW9iaWxlX251bWJlciI6Ijg4OTk3NzY2NTUiLCJlbWFpbF9pZCI6Im1hcmtAZ21haWwuY29tIiwicGFzc3dvcmQiOiI1ZjRkY2MzYjVhYTc2NWQ2MWQ4MzI3ZGViODgyY2Y5OSIsInJlc2V0X3Bhc3N3b3JkX2RhdGUiOm51bGwsImxvY2tfc3RhdHVzIjowLCJpc19hY3RpdmUiOjEsIm1zdF9yb2xlX2lkIjo1LCJtc3Rfc2VydmljZV9sb2NhdGlvbl9pZCI6MSwiY3JlYXRlZF9hdCI6IjIwMjEtMTEtMDNUMDg6MDY6MjMuMDAwWiIsIm1vZGlmaWVkX2F0IjoiMjAyMS0xMS0wM1QwODowNjoyMy4wMDBaIiwicm9sZV9uYW1lIjoiRnJvbnREZXNrIiwic2VydmljZV9sb2NhdGlvbiI6IlNlcnZpY2UgQ2VudGVyIEEiLCJpYXQiOjE3ODA1NzE0NzN9.yS1xSq3RZ2RMtino6uciMYr4UWgWEudsULMj7gZZNnY"
          },
          {
            "key": "Connection",
            "value": "keep-alive"
          },
          {
            "key": "Content-Type",
            "value": "application/json"
          },
          {
            "key": "Origin",
            "value": "http://phoenix.techwithjatin.com"
          },
          {
            "key": "Referer",
            "value": "http://phoenix.techwithjatin.com/"
          },
          {
            "key": "User-Agent",
            "value": "Mozilla/5.0 (Windows NT 10.0; Win64; x64) AppleWebKit/537.36 (KHTML, like Gecko) Chrome/148.0.0.0 Safari/537.36 Edg/148.0.0.0"
          }
        ],
        "body": {
          "mode": "raw",
          "raw": "{\r\n    \"mst_service_location_id\": 0,\r\n    \"mst_platform_id\": 2,\r\n    \"mst_warrenty_status_id\": 1,\r\n    \"mst_oem_id\": 2,\r\n    \"customer\": {\r\n        \"first_name\": \"mohan\",\r\n        \"last_name\": \"kumar\",\r\n        \"mobile_number\": \"9830329479\",\r\n        \"mobile_number_alt\": \"479948739939\",\r\n        \"email_id\": \"sowmiya.narayani02@gmail.com\",\r\n        \"email_id_alt\": \"sowmiya.narayani02@gmail.com\"\r\n    },\r\n    \"customer_address\": {\r\n        \"flat_number\": \"102\",\r\n        \"apartment_name\": \"bren\",\r\n        \"street_name\": \"3057 CEDRIC CT\",\r\n        \"landmark\": \"bus stop\",\r\n        \"area\": \"bangalore\",\r\n        \"pincode\": \"29715\",\r\n        \"country\": \"India\",\r\n        \"state\": \"Andhra Pradesh\"\r\n    },\r\n    \"customer_product\": {\r\n        \"dop\": \"2026-03-25T04:00:00.000Z\",\r\n        \"serial_number\": \"876534219076544\",\r\n        \"imei1\": \"876534219076544\",\r\n        \"imei2\": \"876534219076544\",\r\n        \"popurl\": \"2026-03-25T04:00:00.000Z\",\r\n        \"product_id\": 3,\r\n        \"mst_model_id\": 3\r\n    },\r\n    \"problems\": [\r\n        {\r\n            \"id\": 3,\r\n            \"remark\": \"need to test\"\r\n        }\r\n    ]\r\n}",
          "options": {
            "raw": {
              "language": "json"
            }
          }
        },
        "url": {
          "raw": "{{BASE_URL}}/job/create",
          "host": [
            "{{BASE_URL}}"
          ],
          "path": [
            "job",
            "create"
          ]
        },
        "description": "Generated from cURL: curl 'http://64.227.160.186:9000/v1/job/create' \\\r\n  -H 'Accept: application/json, text/plain, */*' \\\r\n  -H 'Accept-Language: en-US,en;q=0.9' \\\r\n  -H 'Authorization: eyJhbGciOiJIUzI1NiIsInR5cCI6IkpXVCJ9.eyJpZCI6NCwiZmlyc3RfbmFtZSI6ImZkIiwibGFzdF9uYW1lIjoiZmQiLCJsb2dpbl9pZCI6ImlhbWZkIiwibW9iaWxlX251bWJlciI6Ijg4OTk3NzY2NTUiLCJlbWFpbF9pZCI6Im1hcmtAZ21haWwuY29tIiwicGFzc3dvcmQiOiI1ZjRkY2MzYjVhYTc2NWQ2MWQ4MzI3ZGViODgyY2Y5OSIsInJlc2V0X3Bhc3N3b3JkX2RhdGUiOm51bGwsImxvY2tfc3RhdHVzIjowLCJpc19hY3RpdmUiOjEsIm1zdF9yb2xlX2lkIjo1LCJtc3Rfc2VydmljZV9sb2NhdGlvbl9pZCI6MSwiY3JlYXRlZF9hdCI6IjIwMjEtMTEtMDNUMDg6MDY6MjMuMDAwWiIsIm1vZGlmaWVkX2F0IjoiMjAyMS0xMS0wM1QwODowNjoyMy4wMDBaIiwicm9sZV9uYW1lIjoiRnJvbnREZXNrIiwic2VydmljZV9sb2NhdGlvbiI6IlNlcnZpY2UgQ2VudGVyIEEiLCJpYXQiOjE3ODA1NzE0NzN9.yS1xSq3RZ2RMtino6uciMYr4UWgWEudsULMj7gZZNnY' \\\r\n  -H 'Connection: keep-alive' \\\r\n  -H 'Content-Type: application/json' \\\r\n  -H 'Origin: http://phoenix.techwithjatin.com' \\\r\n  -H 'Referer: http://phoenix.techwithjatin.com/' \\\r\n  -H 'User-Agent: Mozilla/5.0 (Windows NT 10.0; Win64; x64) AppleWebKit/537.36 (KHTML, like Gecko) Chrome/148.0.0.0 Safari/537.36 Edg/148.0.0.0' \\\r\n  --data-raw '{\"mst_service_location_id\":0,\"mst_platform_id\":2,\"mst_warrenty_status_id\":1,\"mst_oem_id\":2,\"customer\":{\"first_name\":\"mohan\",\"last_name\":\"kumar\",\"mobile_number\":\"9830329479\",\"mobile_number_alt\":\"479948739939\",\"email_id\":\"sowmiya.narayani02@gmail.com\",\"email_id_alt\":\"sowmiya.narayani02@gmail.com\"},\"customer_address\":{\"flat_number\":\"102\",\"apartment_name\":\"bren\",\"street_name\":\"3057 CEDRIC CT\",\"landmark\":\"bus stop\",\"area\":\"bangalore\",\"pincode\":\"29715\",\"country\":\"India\",\"state\":\"Andhra Pradesh\"},\"customer_product\":{\"dop\":\"2026-03-25T04:00:00.000Z\",\"serial_number\":\"876534219076543\",\"imei1\":\"876534219076543\",\"imei2\":\"876534219076543\",\"popurl\":\"2026-03-25T04:00:00.000Z\",\"product_id\":3,\"mst_model_id\":3},\"problems\":[{\"id\":3,\"remark\":\"need to test\"}]}' \\\r\n  --insecure"
      },
      "response": []
    },
    {
      "name": "jobcreatewith _randomdata",
      "request": {
        "method": "POST",
        "header": [
          {
            "key": "Authorization",
            "value": "eyJhbGciOiJIUzI1NiIsInR5cCI6IkpXVCJ9.eyJpZCI6NCwiZmlyc3RfbmFtZSI6ImZkIiwibGFzdF9uYW1lIjoiZmQiLCJsb2dpbl9pZCI6ImlhbWZkIiwibW9iaWxlX251bWJlciI6Ijg4OTk3NzY2NTUiLCJlbWFpbF9pZCI6Im1hcmtAZ21haWwuY29tIiwicGFzc3dvcmQiOiI1ZjRkY2MzYjVhYTc2NWQ2MWQ4MzI3ZGViODgyY2Y5OSIsInJlc2V0X3Bhc3N3b3JkX2RhdGUiOm51bGwsImxvY2tfc3RhdHVzIjowLCJpc19hY3RpdmUiOjEsIm1zdF9yb2xlX2lkIjo1LCJtc3Rfc2VydmljZV9sb2NhdGlvbl9pZCI6MSwiY3JlYXRlZF9hdCI6IjIwMjEtMTEtMDNUMDg6MDY6MjMuMDAwWiIsIm1vZGlmaWVkX2F0IjoiMjAyMS0xMS0wM1QwODowNjoyMy4wMDBaIiwicm9sZV9uYW1lIjoiRnJvbnREZXNrIiwic2VydmljZV9sb2NhdGlvbiI6IlNlcnZpY2UgQ2VudGVyIEEiLCJpYXQiOjE3ODA1NzE0NzN9.yS1xSq3RZ2RMtino6uciMYr4UWgWEudsULMj7gZZNnY"
          },
          {
            "key": "randomNumber",
            "value": "{{$randomInt}}",
            "type": "text"
          },
          {
            "key": "randomFirstName",
            "value": "{{$randomFirstName}}",
            "type": "text"
          },
          {
            "key": "randomLastName",
            "value": "{{$randomLastName}}",
            "type": "text"
          },
          {
            "key": "randomEmail",
            "value": "{{$randomEmail}}",
            "type": "text"
          },
          {
            "key": "randomPhone",
            "value": "{{$randomPhoneNumber}}",
            "type": "text"
          }
        ],
        "body": {
          "mode": "raw",
          "raw": "{\r\n    \"mst_service_location_id\": 0,\r\n    \"mst_platform_id\": 2,\r\n    \"mst_warrenty_status_id\": 1,\r\n    \"mst_oem_id\": 2,\r\n    \"customer\": {\r\n        \"first_name\": \"{{$randomFirstName}}\",\r\n        \"last_name\": \"{{$randomLastName}}\",\r\n        \"mobile_number\": \"{{$randomPhoneNumber}}\",\r\n        \"mobile_number_alt\": \"479948739939\",\r\n        \"email_id\": \"{{$randomEmail}}\",\r\n        \"email_id_alt\": \"sowmiya.narayani02@gmail.com\"\r\n    },\r\n    \"customer_address\": {\r\n        \"flat_number\": \"102\",\r\n        \"apartment_name\": \"bren\",\r\n        \"street_name\": \"3057 CEDRIC CT\",\r\n        \"landmark\": \"bus stop\",\r\n        \"area\": \"bangalore\",\r\n        \"pincode\": \"29715\",\r\n        \"country\": \"India\",\r\n        \"state\": \"Andhra Pradesh\"\r\n    },\r\n    \"customer_product\": {\r\n        \"dop\": \"2026-03-25T04:00:00.000Z\",\r\n        \"serial_number\": \"876534219076543\",\r\n        \"imei1\": \"876534219076541\",\r\n        \"imei2\": \"876534219076541\",\r\n        \"popurl\": \"2026-03-25T04:00:00.000Z\",\r\n        \"product_id\": 3,\r\n        \"mst_model_id\": 3\r\n    },\r\n    \"problems\": [\r\n        {\r\n            \"id\": 3,\r\n            \"remark\": \"need to test\"\r\n        }\r\n    ]\r\n}",
          "options": {
            "raw": {
              "language": "json"
            }
          }
        },
        "url": {
          "raw": "http://64.227.160.186:9000/v1/job/create",
          "protocol": "http",
          "host": [
            "64",
            "227",
            "160",
            "186"
          ],
          "port": "9000",
          "path": [
            "v1",
            "job",
            "create"
          ]
        },
        "description": "Generated from cURL: curl 'http://64.227.160.186:9000/v1/job/create' \\\r\n  -H 'Accept: application/json, text/plain, */*' \\\r\n  -H 'Accept-Language: en-US,en;q=0.9' \\\r\n  -H 'Authorization: eyJhbGciOiJIUzI1NiIsInR5cCI6IkpXVCJ9.eyJpZCI6NCwiZmlyc3RfbmFtZSI6ImZkIiwibGFzdF9uYW1lIjoiZmQiLCJsb2dpbl9pZCI6ImlhbWZkIiwibW9iaWxlX251bWJlciI6Ijg4OTk3NzY2NTUiLCJlbWFpbF9pZCI6Im1hcmtAZ21haWwuY29tIiwicGFzc3dvcmQiOiI1ZjRkY2MzYjVhYTc2NWQ2MWQ4MzI3ZGViODgyY2Y5OSIsInJlc2V0X3Bhc3N3b3JkX2RhdGUiOm51bGwsImxvY2tfc3RhdHVzIjowLCJpc19hY3RpdmUiOjEsIm1zdF9yb2xlX2lkIjo1LCJtc3Rfc2VydmljZV9sb2NhdGlvbl9pZCI6MSwiY3JlYXRlZF9hdCI6IjIwMjEtMTEtMDNUMDg6MDY6MjMuMDAwWiIsIm1vZGlmaWVkX2F0IjoiMjAyMS0xMS0wM1QwODowNjoyMy4wMDBaIiwicm9sZV9uYW1lIjoiRnJvbnREZXNrIiwic2VydmljZV9sb2NhdGlvbiI6IlNlcnZpY2UgQ2VudGVyIEEiLCJpYXQiOjE3ODA1NzE0NzN9.yS1xSq3RZ2RMtino6uciMYr4UWgWEudsULMj7gZZNnY' \\\r\n  -H 'Connection: keep-alive' \\\r\n  -H 'Content-Type: application/json' \\\r\n  -H 'Origin: http://phoenix.techwithjatin.com' \\\r\n  -H 'Referer: http://phoenix.techwithjatin.com/' \\\r\n  -H 'User-Agent: Mozilla/5.0 (Windows NT 10.0; Win64; x64) AppleWebKit/537.36 (KHTML, like Gecko) Chrome/148.0.0.0 Safari/537.36 Edg/148.0.0.0' \\\r\n  --data-raw '{\"mst_service_location_id\":0,\"mst_platform_id\":2,\"mst_warrenty_status_id\":1,\"mst_oem_id\":2,\"customer\":{\"first_name\":\"mohan\",\"last_name\":\"kumar\",\"mobile_number\":\"9830329479\",\"mobile_number_alt\":\"479948739939\",\"email_id\":\"sowmiya.narayani02@gmail.com\",\"email_id_alt\":\"sowmiya.narayani02@gmail.com\"},\"customer_address\":{\"flat_number\":\"102\",\"apartment_name\":\"bren\",\"street_name\":\"3057 CEDRIC CT\",\"landmark\":\"bus stop\",\"area\":\"bangalore\",\"pincode\":\"29715\",\"country\":\"India\",\"state\":\"Andhra Pradesh\"},\"customer_product\":{\"dop\":\"2026-03-25T04:00:00.000Z\",\"serial_number\":\"876534219076543\",\"imei1\":\"876534219076543\",\"imei2\":\"876534219076543\",\"popurl\":\"2026-03-25T04:00:00.000Z\",\"product_id\":3,\"mst_model_id\":3},\"problems\":[{\"id\":3,\"remark\":\"need to test\"}]}' \\\r\n  --insecure"
      },
      "response": []
    },
    {
      "name": "detailsapi",
      "request": {
        "method": "POST",
        "header": [
          {
            "key": "Accept",
            "value": "application/json, text/plain, */*"
          },
          {
            "key": "Accept-Language",
            "value": "en-US,en;q=0.9"
          },
          {
            "key": "Authorization",
            "value": "eyJhbGciOiJIUzI1NiIsInR5cCI6IkpXVCJ9.eyJpZCI6NCwiZmlyc3RfbmFtZSI6ImZkIiwibGFzdF9uYW1lIjoiZmQiLCJsb2dpbl9pZCI6ImlhbWZkIiwibW9iaWxlX251bWJlciI6Ijg4OTk3NzY2NTUiLCJlbWFpbF9pZCI6Im1hcmtAZ21haWwuY29tIiwicGFzc3dvcmQiOiI1ZjRkY2MzYjVhYTc2NWQ2MWQ4MzI3ZGViODgyY2Y5OSIsInJlc2V0X3Bhc3N3b3JkX2RhdGUiOm51bGwsImxvY2tfc3RhdHVzIjowLCJpc19hY3RpdmUiOjEsIm1zdF9yb2xlX2lkIjo1LCJtc3Rfc2VydmljZV9sb2NhdGlvbl9pZCI6MSwiY3JlYXRlZF9hdCI6IjIwMjEtMTEtMDNUMDg6MDY6MjMuMDAwWiIsIm1vZGlmaWVkX2F0IjoiMjAyMS0xMS0wM1QwODowNjoyMy4wMDBaIiwicm9sZV9uYW1lIjoiRnJvbnREZXNrIiwic2VydmljZV9sb2NhdGlvbiI6IlNlcnZpY2UgQ2VudGVyIEEiLCJpYXQiOjE3ODA1NzE0NzN9.yS1xSq3RZ2RMtino6uciMYr4UWgWEudsULMj7gZZNnY"
          },
          {
            "key": "Connection",
            "value": "keep-alive"
          },
          {
            "key": "Content-Type",
            "value": "application/json"
          },
          {
            "key": "Origin",
            "value": "http://phoenix.techwithjatin.com"
          },
          {
            "key": "Referer",
            "value": "http://phoenix.techwithjatin.com/"
          },
          {
            "key": "User-Agent",
            "value": "Mozilla/5.0 (Windows NT 10.0; Win64; x64) AppleWebKit/537.36 (KHTML, like Gecko) Chrome/148.0.0.0 Safari/537.36 Edg/148.0.0.0"
          }
        ],
        "body": {
          "mode": "raw",
          "raw": "{\"details_key\":\"created_today\"}",
          "options": {
            "raw": {
              "language": "json"
            }
          }
        },
        "url": {
          "raw": "{{BASE_URL}}dashboard/details",
          "host": [
            "{{BASE_URL}}dashboard"
          ],
          "path": [
            "details"
          ]
        },
        "description": "Generated from cURL: curl 'http://64.227.160.186:9000/v1/dashboard/details' \\\r\n  -H 'Accept: application/json, text/plain, */*' \\\r\n  -H 'Accept-Language: en-US,en;q=0.9' \\\r\n  -H 'Authorization: eyJhbGciOiJIUzI1NiIsInR5cCI6IkpXVCJ9.eyJpZCI6NCwiZmlyc3RfbmFtZSI6ImZkIiwibGFzdF9uYW1lIjoiZmQiLCJsb2dpbl9pZCI6ImlhbWZkIiwibW9iaWxlX251bWJlciI6Ijg4OTk3NzY2NTUiLCJlbWFpbF9pZCI6Im1hcmtAZ21haWwuY29tIiwicGFzc3dvcmQiOiI1ZjRkY2MzYjVhYTc2NWQ2MWQ4MzI3ZGViODgyY2Y5OSIsInJlc2V0X3Bhc3N3b3JkX2RhdGUiOm51bGwsImxvY2tfc3RhdHVzIjowLCJpc19hY3RpdmUiOjEsIm1zdF9yb2xlX2lkIjo1LCJtc3Rfc2VydmljZV9sb2NhdGlvbl9pZCI6MSwiY3JlYXRlZF9hdCI6IjIwMjEtMTEtMDNUMDg6MDY6MjMuMDAwWiIsIm1vZGlmaWVkX2F0IjoiMjAyMS0xMS0wM1QwODowNjoyMy4wMDBaIiwicm9sZV9uYW1lIjoiRnJvbnREZXNrIiwic2VydmljZV9sb2NhdGlvbiI6IlNlcnZpY2UgQ2VudGVyIEEiLCJpYXQiOjE3ODA1NzE0NzN9.yS1xSq3RZ2RMtino6uciMYr4UWgWEudsULMj7gZZNnY' \\\r\n  -H 'Connection: keep-alive' \\\r\n  -H 'Content-Type: application/json' \\\r\n  -H 'Origin: http://phoenix.techwithjatin.com' \\\r\n  -H 'Referer: http://phoenix.techwithjatin.com/' \\\r\n  -H 'User-Agent: Mozilla/5.0 (Windows NT 10.0; Win64; x64) AppleWebKit/537.36 (KHTML, like Gecko) Chrome/148.0.0.0 Safari/537.36 Edg/148.0.0.0' \\\r\n  --data-raw '{\"details_key\":\"created_today\"}' \\\r\n  --insecure"
      },
      "response": []
    },
    {
      "name": "superviserpageuserdetails",
      "request": {
        "method": "GET",
        "header": [
          {
            "key": "Authorization",
            "value": "eyJhbGciOiJIUzI1NiIsInR5cCI6IkpXVCJ9.eyJpZCI6MSwiZmlyc3RfbmFtZSI6IkpvaG4iLCJsYXN0X25hbWUiOiJDZW5hIiwibG9naW5faWQiOiJpYW1zdXAiLCJtb2JpbGVfbnVtYmVyIjoiOTk4ODc3ODg5OSIsImVtYWlsX2lkIjoiam9obkBnbWFpbC5jb20iLCJwYXNzd29yZCI6IjVmNGRjYzNiNWFhNzY1ZDYxZDgzMjdkZWI4ODJjZjk5IiwicmVzZXRfcGFzc3dvcmRfZGF0ZSI6bnVsbCwibG9ja19zdGF0dXMiOjAsImlzX2FjdGl2ZSI6MSwibXN0X3JvbGVfaWQiOjIsIm1zdF9zZXJ2aWNlX2xvY2F0aW9uX2lkIjoxLCJjcmVhdGVkX2F0IjoiMjAyMS0xMS0wM1QwODowNjoyMy4wMDBaIiwibW9kaWZpZWRfYXQiOiIyMDIxLTEyLTIwVDA3OjQyOjAwLjAwMFoiLCJyb2xlX25hbWUiOiJTdXBlcnZpc29yIiwic2VydmljZV9sb2NhdGlvbiI6IlNlcnZpY2UgQ2VudGVyIEEiLCJpYXQiOjE3ODA4NjI3NjF9.vBHKuMg8yAQBA2AnQ3CpD8Mnke3pmIsu39rtuXQTek0"
          }
        ],
        "url": {
          "raw": "{{BASE_URL}}userdetails",
          "host": [
            "{{BASE_URL}}userdetails"
          ]
        },
        "description": "Generated from cURL: curl 'http://64.227.160.186:9000/v1/userdetails' \\\r\n  -H 'Accept: application/json, text/plain, */*' \\\r\n  -H 'Accept-Language: en-US,en;q=0.9' \\\r\n  -H 'Authorization: eyJhbGciOiJIUzI1NiIsInR5cCI6IkpXVCJ9.eyJpZCI6MSwiZmlyc3RfbmFtZSI6IkpvaG4iLCJsYXN0X25hbWUiOiJDZW5hIiwibG9naW5faWQiOiJpYW1zdXAiLCJtb2JpbGVfbnVtYmVyIjoiOTk4ODc3ODg5OSIsImVtYWlsX2lkIjoiam9obkBnbWFpbC5jb20iLCJwYXNzd29yZCI6IjVmNGRjYzNiNWFhNzY1ZDYxZDgzMjdkZWI4ODJjZjk5IiwicmVzZXRfcGFzc3dvcmRfZGF0ZSI6bnVsbCwibG9ja19zdGF0dXMiOjAsImlzX2FjdGl2ZSI6MSwibXN0X3JvbGVfaWQiOjIsIm1zdF9zZXJ2aWNlX2xvY2F0aW9uX2lkIjoxLCJjcmVhdGVkX2F0IjoiMjAyMS0xMS0wM1QwODowNjoyMy4wMDBaIiwibW9kaWZpZWRfYXQiOiIyMDIxLTEyLTIwVDA3OjQyOjAwLjAwMFoiLCJyb2xlX25hbWUiOiJTdXBlcnZpc29yIiwic2VydmljZV9sb2NhdGlvbiI6IlNlcnZpY2UgQ2VudGVyIEEiLCJpYXQiOjE3ODA4NjI3NjF9.vBHKuMg8yAQBA2AnQ3CpD8Mnke3pmIsu39rtuXQTek0' \\\r\n  -H 'Connection: keep-alive' \\\r\n  -H 'If-None-Match: W/\"1bc-5jtJRsd0hZILh8Na44eS7Os72ts\"' \\\r\n  -H 'Origin: http://phoenix.techwithjatin.com' \\\r\n  -H 'Referer: http://phoenix.techwithjatin.com/' \\\r\n  -H 'User-Agent: Mozilla/5.0 (Windows NT 10.0; Win64; x64) AppleWebKit/537.36 (KHTML, like Gecko) Chrome/148.0.0.0 Safari/537.36 Edg/148.0.0.0' \\\r\n  --insecure"
      },
      "response": []
    },
    {
      "name": "superviser-pending assign",
      "request": {
        "method": "GET",
        "header": [
          {
            "key": "Accept",
            "value": "application/json, text/plain, */*"
          },
          {
            "key": "Accept-Language",
            "value": "en-US,en;q=0.9"
          },
          {
            "key": "Authorization",
            "value": "eyJhbGciOiJIUzI1NiIsInR5cCI6IkpXVCJ9.eyJpZCI6MSwiZmlyc3RfbmFtZSI6IkpvaG4iLCJsYXN0X25hbWUiOiJDZW5hIiwibG9naW5faWQiOiJpYW1zdXAiLCJtb2JpbGVfbnVtYmVyIjoiOTk4ODc3ODg5OSIsImVtYWlsX2lkIjoiam9obkBnbWFpbC5jb20iLCJwYXNzd29yZCI6IjVmNGRjYzNiNWFhNzY1ZDYxZDgzMjdkZWI4ODJjZjk5IiwicmVzZXRfcGFzc3dvcmRfZGF0ZSI6bnVsbCwibG9ja19zdGF0dXMiOjAsImlzX2FjdGl2ZSI6MSwibXN0X3JvbGVfaWQiOjIsIm1zdF9zZXJ2aWNlX2xvY2F0aW9uX2lkIjoxLCJjcmVhdGVkX2F0IjoiMjAyMS0xMS0wM1QwODowNjoyMy4wMDBaIiwibW9kaWZpZWRfYXQiOiIyMDIxLTEyLTIwVDA3OjQyOjAwLjAwMFoiLCJyb2xlX25hbWUiOiJTdXBlcnZpc29yIiwic2VydmljZV9sb2NhdGlvbiI6IlNlcnZpY2UgQ2VudGVyIEEiLCJpYXQiOjE3ODA4NjI3NjF9.vBHKuMg8yAQBA2AnQ3CpD8Mnke3pmIsu39rtuXQTek0"
          },
          {
            "key": "Connection",
            "value": "keep-alive"
          },
          {
            "key": "Origin",
            "value": "http://phoenix.techwithjatin.com"
          },
          {
            "key": "Referer",
            "value": "http://phoenix.techwithjatin.com/"
          },
          {
            "key": "User-Agent",
            "value": "Mozilla/5.0 (Windows NT 10.0; Win64; x64) AppleWebKit/537.36 (KHTML, like Gecko) Chrome/148.0.0.0 Safari/537.36 Edg/148.0.0.0"
          }
        ],
        "url": {
          "raw": "{{BASE_URL}}/job/pending",
          "host": [
            "{{BASE_URL}}"
          ],
          "path": [
            "job",
            "pending"
          ]
        },
        "description": "Generated from cURL: curl 'http://64.227.160.186:9000/v1/job/pending' \\\r\n  -H 'Accept: application/json, text/plain, */*' \\\r\n  -H 'Accept-Language: en-US,en;q=0.9' \\\r\n  -H 'Authorization: eyJhbGciOiJIUzI1NiIsInR5cCI6IkpXVCJ9.eyJpZCI6MSwiZmlyc3RfbmFtZSI6IkpvaG4iLCJsYXN0X25hbWUiOiJDZW5hIiwibG9naW5faWQiOiJpYW1zdXAiLCJtb2JpbGVfbnVtYmVyIjoiOTk4ODc3ODg5OSIsImVtYWlsX2lkIjoiam9obkBnbWFpbC5jb20iLCJwYXNzd29yZCI6IjVmNGRjYzNiNWFhNzY1ZDYxZDgzMjdkZWI4ODJjZjk5IiwicmVzZXRfcGFzc3dvcmRfZGF0ZSI6bnVsbCwibG9ja19zdGF0dXMiOjAsImlzX2FjdGl2ZSI6MSwibXN0X3JvbGVfaWQiOjIsIm1zdF9zZXJ2aWNlX2xvY2F0aW9uX2lkIjoxLCJjcmVhdGVkX2F0IjoiMjAyMS0xMS0wM1QwODowNjoyMy4wMDBaIiwibW9kaWZpZWRfYXQiOiIyMDIxLTEyLTIwVDA3OjQyOjAwLjAwMFoiLCJyb2xlX25hbWUiOiJTdXBlcnZpc29yIiwic2VydmljZV9sb2NhdGlvbiI6IlNlcnZpY2UgQ2VudGVyIEEiLCJpYXQiOjE3ODA4NjI3NjF9.vBHKuMg8yAQBA2AnQ3CpD8Mnke3pmIsu39rtuXQTek0' \\\r\n  -H 'Connection: keep-alive' \\\r\n  -H 'Origin: http://phoenix.techwithjatin.com' \\\r\n  -H 'Referer: http://phoenix.techwithjatin.com/' \\\r\n  -H 'User-Agent: Mozilla/5.0 (Windows NT 10.0; Win64; x64) AppleWebKit/537.36 (KHTML, like Gecko) Chrome/148.0.0.0 Safari/537.36 Edg/148.0.0.0' \\\r\n  --insecure"
      },
      "response": []
    },
    {
      "name": "superviser-mappedassign",
      "request": {
        "method": "GET",
        "header": [
          {
            "key": "Accept",
            "value": "application/json, text/plain, */*"
          },
          {
            "key": "Accept-Language",
            "value": "en-US,en;q=0.9"
          },
          {
            "key": "Authorization",
            "value": "eyJhbGciOiJIUzI1NiIsInR5cCI6IkpXVCJ9.eyJpZCI6MSwiZmlyc3RfbmFtZSI6IkpvaG4iLCJsYXN0X25hbWUiOiJDZW5hIiwibG9naW5faWQiOiJpYW1zdXAiLCJtb2JpbGVfbnVtYmVyIjoiOTk4ODc3ODg5OSIsImVtYWlsX2lkIjoiam9obkBnbWFpbC5jb20iLCJwYXNzd29yZCI6IjVmNGRjYzNiNWFhNzY1ZDYxZDgzMjdkZWI4ODJjZjk5IiwicmVzZXRfcGFzc3dvcmRfZGF0ZSI6bnVsbCwibG9ja19zdGF0dXMiOjAsImlzX2FjdGl2ZSI6MSwibXN0X3JvbGVfaWQiOjIsIm1zdF9zZXJ2aWNlX2xvY2F0aW9uX2lkIjoxLCJjcmVhdGVkX2F0IjoiMjAyMS0xMS0wM1QwODowNjoyMy4wMDBaIiwibW9kaWZpZWRfYXQiOiIyMDIxLTEyLTIwVDA3OjQyOjAwLjAwMFoiLCJyb2xlX25hbWUiOiJTdXBlcnZpc29yIiwic2VydmljZV9sb2NhdGlvbiI6IlNlcnZpY2UgQ2VudGVyIEEiLCJpYXQiOjE3ODA4NjI3NjF9.vBHKuMg8yAQBA2AnQ3CpD8Mnke3pmIsu39rtuXQTek0"
          },
          {
            "key": "Connection",
            "value": "keep-alive"
          },
          {
            "key": "Origin",
            "value": "http://phoenix.techwithjatin.com"
          },
          {
            "key": "Referer",
            "value": "http://phoenix.techwithjatin.com/"
          },
          {
            "key": "User-Agent",
            "value": "Mozilla/5.0 (Windows NT 10.0; Win64; x64) AppleWebKit/537.36 (KHTML, like Gecko) Chrome/148.0.0.0 Safari/537.36 Edg/148.0.0.0"
          }
        ],
        "url": {
          "raw": "{{BASE_URL}}engineer/mapped",
          "host": [
            "{{BASE_URL}}engineer"
          ],
          "path": [
            "mapped"
          ]
        },
        "description": "Generated from cURL: curl 'http://64.227.160.186:9000/v1/engineer/mapped' \\\r\n  -H 'Accept: application/json, text/plain, */*' \\\r\n  -H 'Accept-Language: en-US,en;q=0.9' \\\r\n  -H 'Authorization: eyJhbGciOiJIUzI1NiIsInR5cCI6IkpXVCJ9.eyJpZCI6MSwiZmlyc3RfbmFtZSI6IkpvaG4iLCJsYXN0X25hbWUiOiJDZW5hIiwibG9naW5faWQiOiJpYW1zdXAiLCJtb2JpbGVfbnVtYmVyIjoiOTk4ODc3ODg5OSIsImVtYWlsX2lkIjoiam9obkBnbWFpbC5jb20iLCJwYXNzd29yZCI6IjVmNGRjYzNiNWFhNzY1ZDYxZDgzMjdkZWI4ODJjZjk5IiwicmVzZXRfcGFzc3dvcmRfZGF0ZSI6bnVsbCwibG9ja19zdGF0dXMiOjAsImlzX2FjdGl2ZSI6MSwibXN0X3JvbGVfaWQiOjIsIm1zdF9zZXJ2aWNlX2xvY2F0aW9uX2lkIjoxLCJjcmVhdGVkX2F0IjoiMjAyMS0xMS0wM1QwODowNjoyMy4wMDBaIiwibW9kaWZpZWRfYXQiOiIyMDIxLTEyLTIwVDA3OjQyOjAwLjAwMFoiLCJyb2xlX25hbWUiOiJTdXBlcnZpc29yIiwic2VydmljZV9sb2NhdGlvbiI6IlNlcnZpY2UgQ2VudGVyIEEiLCJpYXQiOjE3ODA4NjI3NjF9.vBHKuMg8yAQBA2AnQ3CpD8Mnke3pmIsu39rtuXQTek0' \\\r\n  -H 'Connection: keep-alive' \\\r\n  -H 'Origin: http://phoenix.techwithjatin.com' \\\r\n  -H 'Referer: http://phoenix.techwithjatin.com/' \\\r\n  -H 'User-Agent: Mozilla/5.0 (Windows NT 10.0; Win64; x64) AppleWebKit/537.36 (KHTML, like Gecko) Chrome/148.0.0.0 Safari/537.36 Edg/148.0.0.0' \\\r\n  --insecure"
      },
      "response": []
    },
    {
      "name": "engineer/assigned",
      "event": [
        {
          "listen": "prerequest",
          "script": {
            "exec": [
              "console.log(\"Inside pre-request\")"
            ],
            "type": "text/javascript",
            "packages": {},
            "requests": {}
          }
        },
        {
          "listen": "test",
          "script": {
            "exec": [
              "console.log(\"Inside post-request\")"
            ],
            "type": "text/javascript",
            "packages": {},
            "requests": {}
          }
        }
      ],
      "request": {
        "method": "POST",
        "header": [
          {
            "key": "Accept",
            "value": "application/json, text/plain, */*"
          },
          {
            "key": "Accept-Language",
            "value": "en-US,en;q=0.9"
          },
          {
            "key": "Authorization",
            "value": "eyJhbGciOiJIUzI1NiIsInR5cCI6IkpXVCJ9.eyJpZCI6MSwiZmlyc3RfbmFtZSI6IkpvaG4iLCJsYXN0X25hbWUiOiJDZW5hIiwibG9naW5faWQiOiJpYW1zdXAiLCJtb2JpbGVfbnVtYmVyIjoiOTk4ODc3ODg5OSIsImVtYWlsX2lkIjoiam9obkBnbWFpbC5jb20iLCJwYXNzd29yZCI6IjVmNGRjYzNiNWFhNzY1ZDYxZDgzMjdkZWI4ODJjZjk5IiwicmVzZXRfcGFzc3dvcmRfZGF0ZSI6bnVsbCwibG9ja19zdGF0dXMiOjAsImlzX2FjdGl2ZSI6MSwibXN0X3JvbGVfaWQiOjIsIm1zdF9zZXJ2aWNlX2xvY2F0aW9uX2lkIjoxLCJjcmVhdGVkX2F0IjoiMjAyMS0xMS0wM1QwODowNjoyMy4wMDBaIiwibW9kaWZpZWRfYXQiOiIyMDIxLTEyLTIwVDA3OjQyOjAwLjAwMFoiLCJyb2xlX25hbWUiOiJTdXBlcnZpc29yIiwic2VydmljZV9sb2NhdGlvbiI6IlNlcnZpY2UgQ2VudGVyIEEiLCJpYXQiOjE3ODA4NjI3NjF9.vBHKuMg8yAQBA2AnQ3CpD8Mnke3pmIsu39rtuXQTek0"
          },
          {
            "key": "Connection",
            "value": "keep-alive"
          },
          {
            "key": "Content-Type",
            "value": "application/json"
          },
          {
            "key": "Origin",
            "value": "http://phoenix.techwithjatin.com"
          },
          {
            "key": "Referer",
            "value": "http://phoenix.techwithjatin.com/"
          },
          {
            "key": "User-Agent",
            "value": "Mozilla/5.0 (Windows NT 10.0; Win64; x64) AppleWebKit/537.36 (KHTML, like Gecko) Chrome/148.0.0.0 Safari/537.36 Edg/148.0.0.0"
          }
        ],
        "body": {
          "mode": "raw",
          "raw": "{\"job_id\":312062,\"engineer_id\":2}",
          "options": {
            "raw": {
              "language": "json"
            }
          }
        },
        "url": {
          "raw": "{{BASE_URL}}/engineer/assign",
          "host": [
            "{{BASE_URL}}"
          ],
          "path": [
            "engineer",
            "assign"
          ]
        },
        "description": "Generated from cURL: curl 'http://64.227.160.186:9000/v1/engineer/assign' \\\r\n  -H 'Accept: application/json, text/plain, */*' \\\r\n  -H 'Accept-Language: en-US,en;q=0.9' \\\r\n  -H 'Authorization: eyJhbGciOiJIUzI1NiIsInR5cCI6IkpXVCJ9.eyJpZCI6MSwiZmlyc3RfbmFtZSI6IkpvaG4iLCJsYXN0X25hbWUiOiJDZW5hIiwibG9naW5faWQiOiJpYW1zdXAiLCJtb2JpbGVfbnVtYmVyIjoiOTk4ODc3ODg5OSIsImVtYWlsX2lkIjoiam9obkBnbWFpbC5jb20iLCJwYXNzd29yZCI6IjVmNGRjYzNiNWFhNzY1ZDYxZDgzMjdkZWI4ODJjZjk5IiwicmVzZXRfcGFzc3dvcmRfZGF0ZSI6bnVsbCwibG9ja19zdGF0dXMiOjAsImlzX2FjdGl2ZSI6MSwibXN0X3JvbGVfaWQiOjIsIm1zdF9zZXJ2aWNlX2xvY2F0aW9uX2lkIjoxLCJjcmVhdGVkX2F0IjoiMjAyMS0xMS0wM1QwODowNjoyMy4wMDBaIiwibW9kaWZpZWRfYXQiOiIyMDIxLTEyLTIwVDA3OjQyOjAwLjAwMFoiLCJyb2xlX25hbWUiOiJTdXBlcnZpc29yIiwic2VydmljZV9sb2NhdGlvbiI6IlNlcnZpY2UgQ2VudGVyIEEiLCJpYXQiOjE3ODA4NjI3NjF9.vBHKuMg8yAQBA2AnQ3CpD8Mnke3pmIsu39rtuXQTek0' \\\r\n  -H 'Connection: keep-alive' \\\r\n  -H 'Content-Type: application/json' \\\r\n  -H 'Origin: http://phoenix.techwithjatin.com' \\\r\n  -H 'Referer: http://phoenix.techwithjatin.com/' \\\r\n  -H 'User-Agent: Mozilla/5.0 (Windows NT 10.0; Win64; x64) AppleWebKit/537.36 (KHTML, like Gecko) Chrome/148.0.0.0 Safari/537.36 Edg/148.0.0.0' \\\r\n  --data-raw '{\"job_id\":312062,\"engineer_id\":2}' \\\r\n  --insecure"
      },
      "response": []
    },
    {
      "name": "jobcreatewith _randomdata1",
      "event": [
        {
          "listen": "test",
          "script": {
            "exec": [
              "pm.test(\"verify if the status code is 200\",function (){\r",
              "\r",
              "pm.response.to.have.status(200)\r",
              "})\r",
              "\r",
              "pm.test(\"verify if the response time is less than 100ms\", function (){\r",
              "\r",
              "pm.expect(pm.response.responseTime).to.lessThan(700)\r",
              "})"
            ],
            "type": "text/javascript",
            "packages": {},
            "requests": {}
          }
        }
      ],
      "request": {
        "auth": {
          "type": "noauth"
        },
        "method": "POST",
        "header": [
          {
            "key": "Authorization",
            "value": "eyJhbGciOiJIUzI1NiIsInR5cCI6IkpXVCJ9.eyJpZCI6NCwiZmlyc3RfbmFtZSI6ImZkIiwibGFzdF9uYW1lIjoiZmQiLCJsb2dpbl9pZCI6ImlhbWZkIiwibW9iaWxlX251bWJlciI6Ijg4OTk3NzY2NTUiLCJlbWFpbF9pZCI6Im1hcmtAZ21haWwuY29tIiwicGFzc3dvcmQiOiI1ZjRkY2MzYjVhYTc2NWQ2MWQ4MzI3ZGViODgyY2Y5OSIsInJlc2V0X3Bhc3N3b3JkX2RhdGUiOm51bGwsImxvY2tfc3RhdHVzIjowLCJpc19hY3RpdmUiOjEsIm1zdF9yb2xlX2lkIjo1LCJtc3Rfc2VydmljZV9sb2NhdGlvbl9pZCI6MSwiY3JlYXRlZF9hdCI6IjIwMjEtMTEtMDNUMDg6MDY6MjMuMDAwWiIsIm1vZGlmaWVkX2F0IjoiMjAyMS0xMS0wM1QwODowNjoyMy4wMDBaIiwicm9sZV9uYW1lIjoiRnJvbnREZXNrIiwic2VydmljZV9sb2NhdGlvbiI6IlNlcnZpY2UgQ2VudGVyIEEiLCJpYXQiOjE3ODA1NzE0NzN9.yS1xSq3RZ2RMtino6uciMYr4UWgWEudsULMj7gZZNnY"
          },
          {
            "key": "randomNumber",
            "value": "{{$randomInt}}",
            "type": "text"
          },
          {
            "key": "randomFirstName",
            "value": "{{$randomFirstName}}",
            "type": "text"
          },
          {
            "key": "randomLastName",
            "value": "{{$randomLastName}}",
            "type": "text"
          },
          {
            "key": "randomEmail",
            "value": "{{$randomEmail}}",
            "type": "text"
          },
          {
            "key": "randomPhone",
            "value": "{{$randomPhoneNumber}}",
            "type": "text"
          }
        ],
        "body": {
          "mode": "raw",
          "raw": "{\r\n    \"mst_service_location_id\": 0,\r\n    \"mst_platform_id\": 2,\r\n    \"mst_warrenty_status_id\": 1,\r\n    \"mst_oem_id\": 2,\r\n    \"customer\": {\r\n        \"first_name\": \"{{$randomFirstName}}\",\r\n        \"last_name\": \"{{$randomLastName}}\",\r\n        \"mobile_number\": \"{{$randomPhoneNumber}}\",\r\n        \"mobile_number_alt\": \"479948739939\",\r\n        \"email_id\": \"{{$randomEmail}}\",\r\n        \"email_id_alt\": \"sowmiya.narayani02@gmail.com\"\r\n    },\r\n    \"customer_address\": {\r\n        \"flat_number\": \"102\",\r\n        \"apartment_name\": \"bren\",\r\n        \"street_name\": \"3057 CEDRIC CT\",\r\n        \"landmark\": \"bus stop\",\r\n        \"area\": \"bangalore\",\r\n        \"pincode\": \"29715\",\r\n        \"country\": \"India\",\r\n        \"state\": \"Andhra Pradesh\"\r\n    },\r\n    \"customer_product\": {\r\n        \"dop\": \"2026-03-25T04:00:00.000Z\",\r\n        \"serial_number\": \"876534219076543\",\r\n        \"imei1\": \"876534219076120\",\r\n        \"imei2\": \"876534219076120\",\r\n        \"popurl\": \"2026-03-25T04:00:00.000Z\",\r\n        \"product_id\": 3,\r\n        \"mst_model_id\": 3\r\n    },\r\n    \"problems\": [\r\n        {\r\n            \"id\": 3,\r\n            \"remark\": \"need to test\"\r\n        }\r\n    ]\r\n}",
          "options": {
            "raw": {
              "language": "json"
            }
          }
        },
        "url": {
          "raw": "http://64.227.160.186:9000/v1/job/create",
          "protocol": "http",
          "host": [
            "64",
            "227",
            "160",
            "186"
          ],
          "port": "9000",
          "path": [
            "v1",
            "job",
            "create"
          ]
        }
      },
      "response": []
    }
  ],
  "variable": [
    {
      "key": "fdtoken",
      "value": ""
    }
  ]
}